HW4/mux2.sv
module mux2(d0, d1, s, y);

    input wire [4:0] d0;
    input wire [4:0] d1;
    input wire s;
    output logic [4:0] y;
    
    always_comb begin
        y = s ? d1:d0;

    end
endmodule

HW4/mux4.sv
module mux4(d0, d1, d2, d3, s, y);

    input wire [4:0] d0;
    input wire [4:0] d1;
    input wire [4:0] d2;
    input wire [4:0] d3;
    input wire [1:0] s;
    logic [4:0] y1;
    logic  [4:0] y2;
    output logic [4:0] y;

    always_comb begin
        y1 = s[0] ? d3 : d2;
        y2 = s[0] ? d1 : d0;
        y = s[1] ? y1 : y2;
    end
endmodule

HW4/mux32.sv
module mux32(d0, d1, d2, d3, d4, d5, d6, d7, d8, d9, d10, d11, d12, d13, d14, d15, d16, d17,  
            d18, d19, d20, d21, d22, d23, d24, d25, d26, d27, d28, d29, d30, d31, s, y);

    input wire [4:0] d0;
    input wire [4:0] d1;
    input wire [4:0] d2;
    input wire [4:0] d3;
    input wire [4:0] d4;
    input wire [4:0] d5;
    input wire [4:0] d6;
    input wire [4:0] d7;
    input wire [4:0] d8;
    input wire [4:0] d9;
    input wire [4:0] d10;    
    input wire [4:0] d11;
    input wire [4:0] d12;
    input wire [4:0] d13;
    input wire [4:0] d14;
    input wire [4:0] d15;
    input wire [4:0] d16;
    input wire [4:0] d17;
    input wire [4:0] d18;
    input wire [4:0] d19;
    input wire [4:0] d20;
    input wire [4:0] d21;
    input wire [4:0] d22;
    input wire [4:0] d23;    
    input wire [4:0] d24;
    input wire [4:0] d25;
    input wire [4:0] d26;
    input wire [4:0] d27;
    input wire [4:0] d28;
    input wire [4:0] d29;
    input wire [4:0] d30;
    input wire [4:0] d31;
    input wire [4:0] s;
    logic [4:0] i0;
    logic [4:0] i1;
    logic [4:0] i2;
    logic [4:0] i3;
    logic [4:0] i4;
    logic [4:0] i5;
    logic [4:0] i6;
    logic [4:0] i7;
    logic [4:0] i8;
    logic [4:0] i9;
    output logic [4:0] y;

    
    mux4 MUX0 (
    d0[4:0], d1[4:0], d2[4:0], d3[4:0], s[1:0], i0[4:0] 
    );

    mux4 MUX1 (
    d4[4:0], d5[4:0], d6[4:0], d7[4:0], s[1:0], i1[4:0] 
    );

    mux4 MUX2 (
    d8[4:0], d9[4:0], d10[4:0], d11[4:0], s[1:0], i2[4:0] 
    );

    mux4 MUX3 (
    d12[4:0], d13[4:0], d14[4:0], d15[4:0], s[1:0], i3[4:0] 
    );

    mux4 MUX4 (
    d16[4:0], d17[4:0], d18[4:0], d19[4:0], s[1:0], i4[4:0] 
    );

    mux4 MUX5 (
    d20[4:0], d21[4:0], d22[4:0], d23[4:0], s[1:0], i5[4:0] 
    );
    
    mux4 MUX6 (
    d24[4:0], d25[4:0], d26[4:0], d27[4:0], s[1:0], i6[4:0] 
    );

    mux4 MUX7 (
    d28[4:0], d29[4:0], d30[4:0], d31[4:0], s[1:0], i7[4:0] 
    );

    mux4 MUX8 (
    i0[4:0], i1[4:0], i2[4:0], i3[4:0], s[3:2], i8[4:0] 
    );

    mux4 MUX9 (
    i4[4:0], i5[4:0], i6[4:0], i7[4:0], s[3:2], i9[4:0] 
    );

    mux2 MUX10 (
    i8[4:0], i9[4:0], s[4], y[4:0] 
    );


endmodule

HW4/test_mux32.sv
module test_mux32;

  logic [4:0] d0, d1, d2, d3, d4, d5, d6, d7, d8, d9, d10, d11, d12, d13, d14, d15 , d16, d17, d18, d19, d20, d21, d22, d23, d24, d25, d26, d27, d28, d29, d30, d31;
  logic [4:0] s;
  wire [4:0] y;

  mux32 UUT(.d0(d0), .d1(d1), .d2(d2), .d3(d3), .d4(d4), .d5(d5), .d6(d6), .d7(d7), .d8(d8), .d9(d9), .d10(d10), .d11(d11), .d12(d12), .d13(d13), .d14(d14), .d15(d15), .d16(d16), .d17(d17), .d18(d18), .d19(d19), .d20(d20), .d21(d21), .d22(d22), .d23(23), .d24(d24), .d25(d25), .d26(d26), .d27(d27), .d28(d28), .d29(d29), .d30(d30), .d31(d31), .s(s), .y(y));

  initial begin
    $dumpvars(0, UUT);
    $dumpfile("mux32.vcd");

    $display("d0|d1|d2|d3|d4|d5|d6|d7|d8|d9|d10|d11|d12|d13|d14|d15|d16|d17|d18|d19|d20|d21|d22|d23|d24|d25|d26|d27|d28|d29|d30|d31|s |y");
    // testing three random cases

    for (int i = 0; i < 32; i = i + 1) begin 
      
      d0 = 5'b00000 + i;
      d1 = 5'b00001 + i;
      d2 = 5'b00010 + i;
      d3 = 5'b00011 + i;
      d4 = 5'b00100 + i;
      d5 = 5'b00101 + i;
      d6 = 5'b00110 + i;
      d7 = 5'b00111 + i;
      d8 = 5'b01000 + i;
      d9 = 5'b01001 + i;
      d10 = 5'b01010 + i;
      d11 = 5'b01011 + i;
      d12 = 5'b01100 + i;
      d13 = 5'b01101 + i;
      d14 = 5'b01110 + i;
      d15 = 5'b01111 + i;
      d16 = 5'b10000 + i;
      d17 = 5'b10001 + i;
      d18 = 5'b10010 + i;
      d19 = 5'b10011 + i;
      d20 = 5'b10100 + i;
      d21 = 5'b10101 + i;
      d22 = 5'b10110 + i;
      d23 = 5'b10111 + i;
      d24 = 5'b11000 + i;
      d25 = 5'b11001 + i;
      d26 = 5'b11010 + i;
      d27 = 5'b11011 + i;
      d28 = 5'b11100 + i;
      d29 = 5'b11101 + i;
      d30 = 5'b11110 + i;
      d31 = 5'b11111 + i; 
      s = 5'b00000 + i;
      #1 $display("%b|%b|%b|%b|%b|%b|%b|%b|%b|%b|%b|%b|%b|%b|%b|%b|%b|%b|%b|%b|%b|%b|%b|%b|%b|%b|%b|%b|%b|%b|%b|%b|%b|%b", d0, d1, d2, d3, d4, d5, d6, d7, d8, d9, d10, d11, d12, d13, d14, d15 , d16, d17, d18, d19, d20, d21, d22, d23, d24, d25, d26, d27, d28, d29, d30, d31, s, y);
    end
  end

endmodule

HW4/dump.vcd
$date
	Sun Oct 17 12:37:43 2021
$end
$version
	Icarus Verilog
$end
$timescale
	1s
$end
$scope module test_mux32 $end
$scope module UUT $end
$var wire 5 ! d0 [4:0] $end
$var wire 5 " d1 [4:0] $end
$var wire 5 # d10 [4:0] $end
$var wire 5 $ d11 [4:0] $end
$var wire 5 % d12 [4:0] $end
$var wire 5 & d13 [4:0] $end
$var wire 5 ' d14 [4:0] $end
$var wire 5 ( d15 [4:0] $end
$var wire 5 ) d16 [4:0] $end
$var wire 5 * d17 [4:0] $end
$var wire 5 + d18 [4:0] $end
$var wire 5 , d19 [4:0] $end
$var wire 5 - d2 [4:0] $end
$var wire 5 . d20 [4:0] $end
$var wire 5 / d21 [4:0] $end
$var wire 5 0 d22 [4:0] $end
$var wire 5 1 d23 [4:0] $end
$var wire 5 2 d24 [4:0] $end
$var wire 5 3 d25 [4:0] $end
$var wire 5 4 d26 [4:0] $end
$var wire 5 5 d27 [4:0] $end
$var wire 5 6 d28 [4:0] $end
$var wire 5 7 d29 [4:0] $end
$var wire 5 8 d3 [4:0] $end
$var wire 5 9 d30 [4:0] $end
$var wire 5 : d31 [4:0] $end
$var wire 5 ; d4 [4:0] $end
$var wire 5 < d5 [4:0] $end
$var wire 5 = d6 [4:0] $end
$var wire 5 > d7 [4:0] $end
$var wire 5 ? d8 [4:0] $end
$var wire 5 @ d9 [4:0] $end
$var wire 5 A s [4:0] $end
$var wire 5 B y [4:0] $end
$var wire 5 C i9 [4:0] $end
$var wire 5 D i8 [4:0] $end
$var wire 5 E i7 [4:0] $end
$var wire 5 F i6 [4:0] $end
$var wire 5 G i5 [4:0] $end
$var wire 5 H i4 [4:0] $end
$var wire 5 I i3 [4:0] $end
$var wire 5 J i2 [4:0] $end
$var wire 5 K i1 [4:0] $end
$var wire 5 L i0 [4:0] $end
$scope module MUX0 $end
$var wire 5 M d0 [4:0] $end
$var wire 5 N d1 [4:0] $end
$var wire 5 O d2 [4:0] $end
$var wire 5 P d3 [4:0] $end
$var wire 2 Q s [1:0] $end
$var reg 5 R y [4:0] $end
$var reg 5 S y1 [4:0] $end
$var reg 5 T y2 [4:0] $end
$upscope $end
$scope module MUX1 $end
$var wire 5 U d0 [4:0] $end
$var wire 5 V d1 [4:0] $end
$var wire 5 W d2 [4:0] $end
$var wire 5 X d3 [4:0] $end
$var wire 2 Y s [1:0] $end
$var reg 5 Z y [4:0] $end
$var reg 5 [ y1 [4:0] $end
$var reg 5 \ y2 [4:0] $end
$upscope $end
$scope module MUX10 $end
$var wire 1 ] s $end
$var wire 5 ^ d1 [4:0] $end
$var wire 5 _ d0 [4:0] $end
$var reg 5 ` y [4:0] $end
$upscope $end
$scope module MUX2 $end
$var wire 5 a d0 [4:0] $end
$var wire 5 b d1 [4:0] $end
$var wire 5 c d2 [4:0] $end
$var wire 5 d d3 [4:0] $end
$var wire 2 e s [1:0] $end
$var reg 5 f y [4:0] $end
$var reg 5 g y1 [4:0] $end
$var reg 5 h y2 [4:0] $end
$upscope $end
$scope module MUX3 $end
$var wire 5 i d0 [4:0] $end
$var wire 5 j d1 [4:0] $end
$var wire 5 k d2 [4:0] $end
$var wire 5 l d3 [4:0] $end
$var wire 2 m s [1:0] $end
$var reg 5 n y [4:0] $end
$var reg 5 o y1 [4:0] $end
$var reg 5 p y2 [4:0] $end
$upscope $end
$scope module MUX4 $end
$var wire 5 q d0 [4:0] $end
$var wire 5 r d1 [4:0] $end
$var wire 5 s d2 [4:0] $end
$var wire 5 t d3 [4:0] $end
$var wire 2 u s [1:0] $end
$var reg 5 v y [4:0] $end
$var reg 5 w y1 [4:0] $end
$var reg 5 x y2 [4:0] $end
$upscope $end
$scope module MUX5 $end
$var wire 5 y d0 [4:0] $end
$var wire 5 z d1 [4:0] $end
$var wire 5 { d2 [4:0] $end
$var wire 5 | d3 [4:0] $end
$var wire 2 } s [1:0] $end
$var reg 5 ~ y [4:0] $end
$var reg 5 !" y1 [4:0] $end
$var reg 5 "" y2 [4:0] $end
$upscope $end
$scope module MUX6 $end
$var wire 5 #" d0 [4:0] $end
$var wire 5 $" d1 [4:0] $end
$var wire 5 %" d2 [4:0] $end
$var wire 5 &" d3 [4:0] $end
$var wire 2 '" s [1:0] $end
$var reg 5 (" y [4:0] $end
$var reg 5 )" y1 [4:0] $end
$var reg 5 *" y2 [4:0] $end
$upscope $end
$scope module MUX7 $end
$var wire 5 +" d0 [4:0] $end
$var wire 5 ," d1 [4:0] $end
$var wire 5 -" d2 [4:0] $end
$var wire 5 ." d3 [4:0] $end
$var wire 2 /" s [1:0] $end
$var reg 5 0" y [4:0] $end
$var reg 5 1" y1 [4:0] $end
$var reg 5 2" y2 [4:0] $end
$upscope $end
$scope module MUX8 $end
$var wire 5 3" d0 [4:0] $end
$var wire 5 4" d1 [4:0] $end
$var wire 5 5" d2 [4:0] $end
$var wire 5 6" d3 [4:0] $end
$var wire 2 7" s [1:0] $end
$var reg 5 8" y [4:0] $end
$var reg 5 9" y1 [4:0] $end
$var reg 5 :" y2 [4:0] $end
$upscope $end
$scope module MUX9 $end
$var wire 5 ;" d0 [4:0] $end
$var wire 5 <" d1 [4:0] $end
$var wire 5 =" d2 [4:0] $end
$var wire 5 >" d3 [4:0] $end
$var wire 2 ?" s [1:0] $end
$var reg 5 @" y [4:0] $end
$var reg 5 A" y1 [4:0] $end
$var reg 5 B" y2 [4:0] $end
$upscope $end
$upscope $end
$upscope $end
$enddefinitions $end
#0
$dumpvars
b10000 B"
b11000 A"
b10000 @"
b0 ?"
b11100 >"
b11000 ="
b10100 <"
b10000 ;"
b0 :"
b1000 9"
b0 8"
b0 7"
b1100 6"
b1000 5"
b100 4"
b0 3"
b11100 2"
b11110 1"
b11100 0"
b0 /"
b11111 ."
b11110 -"
b11101 ,"
b11100 +"
b11000 *"
b11010 )"
b11000 ("
b0 '"
b11011 &"
b11010 %"
b11001 $"
b11000 #"
b10100 ""
b10110 !"
b10100 ~
b0 }
b10111 |
b10110 {
b10101 z
b10100 y
b10000 x
b10010 w
b10000 v
b0 u
b10011 t
b10010 s
b10001 r
b10000 q
b1100 p
b1110 o
b1100 n
b0 m
b1111 l
b1110 k
b1101 j
b1100 i
b1000 h
b1010 g
b1000 f
b0 e
b1011 d
b1010 c
b1001 b
b1000 a
b0 `
b0 _
b10000 ^
0]
b100 \
b110 [
b100 Z
b0 Y
b111 X
b110 W
b101 V
b100 U
b0 T
b10 S
b0 R
b0 Q
b11 P
b10 O
b1 N
b0 M
b0 L
b100 K
b1000 J
b1100 I
b10000 H
b10100 G
b11000 F
b11100 E
b0 D
b10000 C
b0 B
b0 A
b1001 @
b1000 ?
b111 >
b110 =
b101 <
b100 ;
b11111 :
b11110 9
b11 8
b11101 7
b11100 6
b11011 5
b11010 4
b11001 3
b11000 2
b10111 1
b10110 0
b10101 /
b10100 .
b10 -
b10011 ,
b10010 +
b10001 *
b10000 )
b1111 (
b1110 '
b1101 &
b1100 %
b1011 $
b1010 #
b1 "
b0 !
$end
#1
b10 B
b10 `
b10010 C
b10010 ^
b10010 @"
b10010 B"
b11010 A"
b10 D
b10 _
b10 8"
b10 :"
b1010 9"
b1 Q
b1 Y
b1 e
b1 m
b1 u
b1 }
b1 '"
b1 /"
b11110 E
b11110 0"
b11110 >"
b11110 2"
b0 1"
b11010 F
b11010 ("
b11010 ="
b11010 *"
b11100 )"
b10110 G
b10110 ~
b10110 <"
b10110 ""
b10111 !"
b10010 H
b10010 v
b10010 ;"
b10010 x
b10100 w
b1110 I
b1110 n
b1110 6"
b1110 p
b10000 o
b1010 J
b1010 f
b1010 5"
b1010 h
b1100 g
b110 K
b110 Z
b110 4"
b110 \
b1000 [
b10 L
b10 R
b10 3"
b10 T
b100 S
b1 A
b0 :
b0 ."
b11111 9
b11111 -"
b11110 7
b11110 ,"
b11101 6
b11101 +"
b11100 5
b11100 &"
b11011 4
b11011 %"
b11010 3
b11010 $"
b11001 2
b11001 #"
b10111 0
b10111 {
b10110 /
b10110 z
b10101 .
b10101 y
b10100 ,
b10100 t
b10011 +
b10011 s
b10010 *
b10010 r
b10001 )
b10001 q
b10000 (
b10000 l
b1111 '
b1111 k
b1110 &
b1110 j
b1101 %
b1101 i
b1100 $
b1100 d
b1011 #
b1011 c
b1010 @
b1010 b
b1001 ?
b1001 a
b1000 >
b1000 X
b111 =
b111 W
b110 <
b110 V
b101 ;
b101 U
b100 8
b100 P
b11 -
b11 O
b10 "
b10 N
b1 !
b1 M
#2
b100 B
b100 `
b11000 !"
b10100 C
b10100 ^
b10100 @"
b10100 B"
b11100 A"
b100 D
b100 _
b100 8"
b100 :"
b1100 9"
b10 Q
b10 Y
b10 e
b10 m
b10 u
b10 }
b10 '"
b10 /"
b0 E
b0 0"
b0 >"
b11110 2"
b0 1"
b11100 F
b11100 ("
b11100 ="
b11010 *"
b11100 )"
b11000 G
b11000 ~
b11000 <"
b10110 ""
b10100 H
b10100 v
b10100 ;"
b10010 x
b10100 w
b10000 I
b10000 n
b10000 6"
b1110 p
b10000 o
b1100 J
b1100 f
b1100 5"
b1010 h
b1100 g
b1000 K
b1000 Z
b1000 4"
b110 \
b1000 [
b100 L
b100 R
b100 3"
b10 T
b100 S
b10 A
b1 :
b1 ."
b0 9
b0 -"
b11111 7
b11111 ,"
b11110 6
b11110 +"
b11101 5
b11101 &"
b11100 4
b11100 %"
b11011 3
b11011 $"
b11010 2
b11010 #"
b11000 0
b11000 {
b10111 /
b10111 z
b10110 .
b10110 y
b10101 ,
b10101 t
b10100 +
b10100 s
b10011 *
b10011 r
b10010 )
b10010 q
b10001 (
b10001 l
b10000 '
b10000 k
b1111 &
b1111 j
b1110 %
b1110 i
b1101 $
b1101 d
b1100 #
b1100 c
b1011 @
b1011 b
b1010 ?
b1010 a
b1001 >
b1001 X
b1000 =
b1000 W
b111 <
b111 V
b110 ;
b110 U
b101 8
b101 P
b100 -
b100 O
b11 "
b11 N
b10 !
b10 M
#3
b110 B
b110 `
b10110 C
b10110 ^
b10110 @"
b10110 B"
b11110 A"
b110 D
b110 _
b110 8"
b110 :"
b1110 9"
b11 Q
b11 Y
b11 e
b11 m
b11 u
b11 }
b11 '"
b11 /"
b10 E
b10 0"
b10 >"
b0 2"
b10 1"
b11110 F
b11110 ("
b11110 ="
b11100 *"
b11110 )"
b10111 G
b10111 ~
b10111 <"
b11000 ""
b10111 !"
b10110 H
b10110 v
b10110 ;"
b10100 x
b10110 w
b10010 I
b10010 n
b10010 6"
b10000 p
b10010 o
b1110 J
b1110 f
b1110 5"
b1100 h
b1110 g
b1010 K
b1010 Z
b1010 4"
b1000 \
b1010 [
b110 L
b110 R
b110 3"
b100 T
b110 S
b11 A
b10 :
b10 ."
b1 9
b1 -"
b0 7
b0 ,"
b11111 6
b11111 +"
b11110 5
b11110 &"
b11101 4
b11101 %"
b11100 3
b11100 $"
b11011 2
b11011 #"
b11001 0
b11001 {
b11000 /
b11000 z
b10111 .
b10111 y
b10110 ,
b10110 t
b10101 +
b10101 s
b10100 *
b10100 r
b10011 )
b10011 q
b10010 (
b10010 l
b10001 '
b10001 k
b10000 &
b10000 j
b1111 %
b1111 i
b1110 $
b1110 d
b1101 #
b1101 c
b1100 @
b1100 b
b1011 ?
b1011 a
b1010 >
b1010 X
b1001 =
b1001 W
b1000 <
b1000 V
b111 ;
b111 U
b110 8
b110 P
b101 -
b101 O
b100 "
b100 N
b11 !
b11 M
#4
b1000 B
b1000 `
b11000 G
b11000 ~
b11000 <"
b11010 !"
b11000 C
b11000 ^
b11000 @"
b11000 B"
b0 A"
b1000 D
b1000 _
b1000 8"
b1000 :"
b10000 9"
b0 Q
b0 Y
b0 e
b0 m
b0 u
b0 }
b0 '"
b0 /"
b1 7"
b1 ?"
b0 E
b0 0"
b0 >"
b0 2"
b10 1"
b11100 F
b11100 ("
b11100 ="
b11100 *"
b11110 )"
b11000 ""
b10100 H
b10100 v
b10100 ;"
b10100 x
b10110 w
b10000 I
b10000 n
b10000 6"
b10000 p
b10010 o
b1100 J
b1100 f
b1100 5"
b1100 h
b1110 g
b1000 K
b1000 Z
b1000 4"
b1000 \
b1010 [
b100 L
b100 R
b100 3"
b100 T
b110 S
b100 A
b11 :
b11 ."
b10 9
b10 -"
b1 7
b1 ,"
b0 6
b0 +"
b11111 5
b11111 &"
b11110 4
b11110 %"
b11101 3
b11101 $"
b11100 2
b11100 #"
b11010 0
b11010 {
b11001 /
b11001 z
b11000 .
b11000 y
b10111 ,
b10111 t
b10110 +
b10110 s
b10101 *
b10101 r
b10100 )
b10100 q
b10011 (
b10011 l
b10010 '
b10010 k
b10001 &
b10001 j
b10000 %
b10000 i
b1111 $
b1111 d
b1110 #
b1110 c
b1101 @
b1101 b
b1100 ?
b1100 a
b1011 >
b1011 X
b1010 =
b1010 W
b1001 <
b1001 V
b1000 ;
b1000 U
b111 8
b111 P
b110 -
b110 O
b101 "
b101 N
b100 !
b100 M
#5
b1010 B
b1010 `
b11010 C
b11010 ^
b11010 @"
b11010 B"
b10 A"
b1010 D
b1010 _
b1010 8"
b1010 :"
b10010 9"
b1 Q
b1 Y
b1 e
b1 m
b1 u
b1 }
b1 '"
b1 /"
b10 E
b10 0"
b10 >"
b10 2"
b100 1"
b11110 F
b11110 ("
b11110 ="
b11110 *"
b0 )"
b11010 G
b11010 ~
b11010 <"
b11010 ""
b10111 !"
b10110 H
b10110 v
b10110 ;"
b10110 x
b11000 w
b10010 I
b10010 n
b10010 6"
b10010 p
b10100 o
b1110 J
b1110 f
b1110 5"
b1110 h
b10000 g
b1010 K
b1010 Z
b1010 4"
b1010 \
b1100 [
b110 L
b110 R
b110 3"
b110 T
b1000 S
b101 A
b100 :
b100 ."
b11 9
b11 -"
b10 7
b10 ,"
b1 6
b1 +"
b0 5
b0 &"
b11111 4
b11111 %"
b11110 3
b11110 $"
b11101 2
b11101 #"
b11011 0
b11011 {
b11010 /
b11010 z
b11001 .
b11001 y
b11000 ,
b11000 t
b10111 +
b10111 s
b10110 *
b10110 r
b10101 )
b10101 q
b10100 (
b10100 l
b10011 '
b10011 k
b10010 &
b10010 j
b10001 %
b10001 i
b10000 $
b10000 d
b1111 #
b1111 c
b1110 @
b1110 b
b1101 ?
b1101 a
b1100 >
b1100 X
b1011 =
b1011 W
b1010 <
b1010 V
b1001 ;
b1001 U
b1000 8
b1000 P
b111 -
b111 O
b110 "
b110 N
b101 !
b101 M
#6
b1100 B
b1100 `
b11100 !"
b11100 C
b11100 ^
b11100 @"
b11100 B"
b100 A"
b1100 D
b1100 _
b1100 8"
b1100 :"
b10100 9"
b10 Q
b10 Y
b10 e
b10 m
b10 u
b10 }
b10 '"
b10 /"
b100 E
b100 0"
b100 >"
b10 2"
b100 1"
b0 F
b0 ("
b0 ="
b11110 *"
b0 )"
b11100 G
b11100 ~
b11100 <"
b11010 ""
b11000 H
b11000 v
b11000 ;"
b10110 x
b11000 w
b10100 I
b10100 n
b10100 6"
b10010 p
b10100 o
b10000 J
b10000 f
b10000 5"
b1110 h
b10000 g
b1100 K
b1100 Z
b1100 4"
b1010 \
b1100 [
b1000 L
b1000 R
b1000 3"
b110 T
b1000 S
b110 A
b101 :
b101 ."
b100 9
b100 -"
b11 7
b11 ,"
b10 6
b10 +"
b1 5
b1 &"
b0 4
b0 %"
b11111 3
b11111 $"
b11110 2
b11110 #"
b11100 0
b11100 {
b11011 /
b11011 z
b11010 .
b11010 y
b11001 ,
b11001 t
b11000 +
b11000 s
b10111 *
b10111 r
b10110 )
b10110 q
b10101 (
b10101 l
b10100 '
b10100 k
b10011 &
b10011 j
b10010 %
b10010 i
b10001 $
b10001 d
b10000 #
b10000 c
b1111 @
b1111 b
b1110 ?
b1110 a
b1101 >
b1101 X
b1100 =
b1100 W
b1011 <
b1011 V
b1010 ;
b1010 U
b1001 8
b1001 P
b1000 -
b1000 O
b111 "
b111 N
b110 !
b110 M
#7
b1110 B
b1110 `
b10111 C
b10111 ^
b10111 @"
b10111 B"
b110 A"
b1110 D
b1110 _
b1110 8"
b1110 :"
b10110 9"
b11 Q
b11 Y
b11 e
b11 m
b11 u
b11 }
b11 '"
b11 /"
b110 E
b110 0"
b110 >"
b100 2"
b110 1"
b10 F
b10 ("
b10 ="
b0 *"
b10 )"
b10111 G
b10111 ~
b10111 <"
b11100 ""
b10111 !"
b11010 H
b11010 v
b11010 ;"
b11000 x
b11010 w
b10110 I
b10110 n
b10110 6"
b10100 p
b10110 o
b10010 J
b10010 f
b10010 5"
b10000 h
b10010 g
b1110 K
b1110 Z
b1110 4"
b1100 \
b1110 [
b1010 L
b1010 R
b1010 3"
b1000 T
b1010 S
b111 A
b110 :
b110 ."
b101 9
b101 -"
b100 7
b100 ,"
b11 6
b11 +"
b10 5
b10 &"
b1 4
b1 %"
b0 3
b0 $"
b11111 2
b11111 #"
b11101 0
b11101 {
b11100 /
b11100 z
b11011 .
b11011 y
b11010 ,
b11010 t
b11001 +
b11001 s
b11000 *
b11000 r
b10111 )
b10111 q
b10110 (
b10110 l
b10101 '
b10101 k
b10100 &
b10100 j
b10011 %
b10011 i
b10010 $
b10010 d
b10001 #
b10001 c
b10000 @
b10000 b
b1111 ?
b1111 a
b1110 >
b1110 X
b1101 =
b1101 W
b1100 <
b1100 V
b1011 ;
b1011 U
b1010 8
b1010 P
b1001 -
b1001 O
b1000 "
b1000 N
b111 !
b111 M
#8
b10000 B
b10000 `
b11100 G
b11100 ~
b11100 <"
b11110 !"
b0 C
b0 ^
b0 @"
b11000 B"
b0 A"
b10000 D
b10000 _
b10000 8"
b1000 :"
b10000 9"
b0 Q
b0 Y
b0 e
b0 m
b0 u
b0 }
b0 '"
b0 /"
b10 7"
b10 ?"
b100 E
b100 0"
b100 >"
b100 2"
b110 1"
b0 F
b0 ("
b0 ="
b0 *"
b10 )"
b11100 ""
b11000 H
b11000 v
b11000 ;"
b11000 x
b11010 w
b10100 I
b10100 n
b10100 6"
b10100 p
b10110 o
b10000 J
b10000 f
b10000 5"
b10000 h
b10010 g
b1100 K
b1100 Z
b1100 4"
b1100 \
b1110 [
b1000 L
b1000 R
b1000 3"
b1000 T
b1010 S
b1000 A
b111 :
b111 ."
b110 9
b110 -"
b101 7
b101 ,"
b100 6
b100 +"
b11 5
b11 &"
b10 4
b10 %"
b1 3
b1 $"
b0 2
b0 #"
b11110 0
b11110 {
b11101 /
b11101 z
b11100 .
b11100 y
b11011 ,
b11011 t
b11010 +
b11010 s
b11001 *
b11001 r
b11000 )
b11000 q
b10111 (
b10111 l
b10110 '
b10110 k
b10101 &
b10101 j
b10100 %
b10100 i
b10011 $
b10011 d
b10010 #
b10010 c
b10001 @
b10001 b
b10000 ?
b10000 a
b1111 >
b1111 X
b1110 =
b1110 W
b1101 <
b1101 V
b1100 ;
b1100 U
b1011 8
b1011 P
b1010 -
b1010 O
b1001 "
b1001 N
b1000 !
b1000 M
#9
b10010 B
b10010 `
b10 C
b10 ^
b10 @"
b11010 B"
b10 A"
b10010 D
b10010 _
b10010 8"
b1010 :"
b10010 9"
b1 Q
b1 Y
b1 e
b1 m
b1 u
b1 }
b1 '"
b1 /"
b110 E
b110 0"
b110 >"
b110 2"
b1000 1"
b10 F
b10 ("
b10 ="
b10 *"
b100 )"
b11110 G
b11110 ~
b11110 <"
b11110 ""
b10111 !"
b11010 H
b11010 v
b11010 ;"
b11010 x
b11100 w
b10110 I
b10110 n
b10110 6"
b10110 p
b11000 o
b10010 J
b10010 f
b10010 5"
b10010 h
b10100 g
b1110 K
b1110 Z
b1110 4"
b1110 \
b10000 [
b1010 L
b1010 R
b1010 3"
b1010 T
b1100 S
b1001 A
b1000 :
b1000 ."
b111 9
b111 -"
b110 7
b110 ,"
b101 6
b101 +"
b100 5
b100 &"
b11 4
b11 %"
b10 3
b10 $"
b1 2
b1 #"
b11111 0
b11111 {
b11110 /
b11110 z
b11101 .
b11101 y
b11100 ,
b11100 t
b11011 +
b11011 s
b11010 *
b11010 r
b11001 )
b11001 q
b11000 (
b11000 l
b10111 '
b10111 k
b10110 &
b10110 j
b10101 %
b10101 i
b10100 $
b10100 d
b10011 #
b10011 c
b10010 @
b10010 b
b10001 ?
b10001 a
b10000 >
b10000 X
b1111 =
b1111 W
b1110 <
b1110 V
b1101 ;
b1101 U
b1100 8
b1100 P
b1011 -
b1011 O
b1010 "
b1010 N
b1001 !
b1001 M
#10
b10100 B
b10100 `
b0 !"
b100 C
b100 ^
b100 @"
b11100 B"
b100 A"
b10100 D
b10100 _
b10100 8"
b1100 :"
b10100 9"
b10 Q
b10 Y
b10 e
b10 m
b10 u
b10 }
b10 '"
b10 /"
b1000 E
b1000 0"
b1000 >"
b110 2"
b1000 1"
b100 F
b100 ("
b100 ="
b10 *"
b100 )"
b0 G
b0 ~
b0 <"
b11110 ""
b11100 H
b11100 v
b11100 ;"
b11010 x
b11100 w
b11000 I
b11000 n
b11000 6"
b10110 p
b11000 o
b10100 J
b10100 f
b10100 5"
b10010 h
b10100 g
b10000 K
b10000 Z
b10000 4"
b1110 \
b10000 [
b1100 L
b1100 R
b1100 3"
b1010 T
b1100 S
b1010 A
b1001 :
b1001 ."
b1000 9
b1000 -"
b111 7
b111 ,"
b110 6
b110 +"
b101 5
b101 &"
b100 4
b100 %"
b11 3
b11 $"
b10 2
b10 #"
b0 0
b0 {
b11111 /
b11111 z
b11110 .
b11110 y
b11101 ,
b11101 t
b11100 +
b11100 s
b11011 *
b11011 r
b11010 )
b11010 q
b11001 (
b11001 l
b11000 '
b11000 k
b10111 &
b10111 j
b10110 %
b10110 i
b10101 $
b10101 d
b10100 #
b10100 c
b10011 @
b10011 b
b10010 ?
b10010 a
b10001 >
b10001 X
b10000 =
b10000 W
b1111 <
b1111 V
b1110 ;
b1110 U
b1101 8
b1101 P
b1100 -
b1100 O
b1011 "
b1011 N
b1010 !
b1010 M
#11
b10110 B
b10110 `
b110 C
b110 ^
b110 @"
b11110 B"
b110 A"
b10110 D
b10110 _
b10110 8"
b1110 :"
b10110 9"
b11 Q
b11 Y
b11 e
b11 m
b11 u
b11 }
b11 '"
b11 /"
b1010 E
b1010 0"
b1010 >"
b1000 2"
b1010 1"
b110 F
b110 ("
b110 ="
b100 *"
b110 )"
b10111 G
b10111 ~
b10111 <"
b0 ""
b10111 !"
b11110 H
b11110 v
b11110 ;"
b11100 x
b11110 w
b11010 I
b11010 n
b11010 6"
b11000 p
b11010 o
b10110 J
b10110 f
b10110 5"
b10100 h
b10110 g
b10010 K
b10010 Z
b10010 4"
b10000 \
b10010 [
b1110 L
b1110 R
b1110 3"
b1100 T
b1110 S
b1011 A
b1010 :
b1010 ."
b1001 9
b1001 -"
b1000 7
b1000 ,"
b111 6
b111 +"
b110 5
b110 &"
b101 4
b101 %"
b100 3
b100 $"
b11 2
b11 #"
b1 0
b1 {
b0 /
b0 z
b11111 .
b11111 y
b11110 ,
b11110 t
b11101 +
b11101 s
b11100 *
b11100 r
b11011 )
b11011 q
b11010 (
b11010 l
b11001 '
b11001 k
b11000 &
b11000 j
b10111 %
b10111 i
b10110 $
b10110 d
b10101 #
b10101 c
b10100 @
b10100 b
b10011 ?
b10011 a
b10010 >
b10010 X
b10001 =
b10001 W
b10000 <
b10000 V
b1111 ;
b1111 U
b1110 8
b1110 P
b1101 -
b1101 O
b1100 "
b1100 N
b1011 !
b1011 M
